{
  "_format": "hh-sol-cache-2",
  "files": {
    "/home/arpit/blockchain projects/CryptoDevsDAO/hardhat-code/contracts/CryptoDevsDAO.sol": {
      "lastModificationDate": 1675753963987,
      "contentHash": "37a33501750c218ca78c5b98ca16fd29",
      "sourceName": "contracts/CryptoDevsDAO.sol",
      "solcConfig": {
        "version": "0.8.17",
        "settings": {
          "optimizer": {
            "enabled": false,
            "runs": 200
          },
          "outputSelection": {
            "*": {
              "*": [
                "abi",
                "evm.bytecode",
                "evm.deployedBytecode",
                "evm.methodIdentifiers",
                "metadata"
              ],
              "": [
                "ast"
              ]
            }
          }
        }
      },
      "imports": [
        "@openzeppelin/contracts/access/Ownable.sol",
        "hardhat/console.sol"
      ],
      "versionPragmas": [
        "^0.8.1"
      ],
      "artifacts": [
        "CryptoDevsDAO",
        "ICryptoDevsNFT",
        "IFakeNFTMarketplace"
      ]
    },
    "/home/arpit/blockchain projects/CryptoDevsDAO/hardhat-code/node_modules/hardhat/console.sol": {
      "lastModificationDate": 1675501449479,
      "contentHash": "4ff3cd2f6272c9a6516e9ee4f2b967d3",
      "sourceName": "hardhat/console.sol",
      "solcConfig": {
        "version": "0.8.17",
        "settings": {
          "optimizer": {
            "enabled": false,
            "runs": 200
          },
          "outputSelection": {
            "*": {
              "*": [
                "abi",
                "evm.bytecode",
                "evm.deployedBytecode",
                "evm.methodIdentifiers",
                "metadata"
              ],
              "": [
                "ast"
              ]
            }
          }
        }
      },
      "imports": [],
      "versionPragmas": [
        ">= 0.4.22 <0.9.0"
      ],
      "artifacts": [
        "console"
      ]
    },
    "/home/arpit/blockchain projects/CryptoDevsDAO/hardhat-code/node_modules/@openzeppelin/contracts/access/Ownable.sol": {
      "lastModificationDate": 1675688103209,
      "contentHash": "e436cea06129be2c73cda4b1acc848b5",
      "sourceName": "@openzeppelin/contracts/access/Ownable.sol",
      "solcConfig": {
        "version": "0.8.17",
        "settings": {
          "optimizer": {
            "enabled": false,
            "runs": 200
          },
          "outputSelection": {
            "*": {
              "*": [
                "abi",
                "evm.bytecode",
                "evm.deployedBytecode",
                "evm.methodIdentifiers",
                "metadata"
              ],
              "": [
                "ast"
              ]
            }
          }
        }
      },
      "imports": [
        "../utils/Context.sol"
      ],
      "versionPragmas": [
        "^0.8.0"
      ],
      "artifacts": [
        "Ownable"
      ]
    },
    "/home/arpit/blockchain projects/CryptoDevsDAO/hardhat-code/node_modules/@openzeppelin/contracts/utils/Context.sol": {
      "lastModificationDate": 1675688103209,
      "contentHash": "5f2c5c4b6af2dd4551027144797bc8be",
      "sourceName": "@openzeppelin/contracts/utils/Context.sol",
      "solcConfig": {
        "version": "0.8.17",
        "settings": {
          "optimizer": {
            "enabled": false,
            "runs": 200
          },
          "outputSelection": {
            "*": {
              "*": [
                "abi",
                "evm.bytecode",
                "evm.deployedBytecode",
                "evm.methodIdentifiers",
                "metadata"
              ],
              "": [
                "ast"
              ]
            }
          }
        }
      },
      "imports": [],
      "versionPragmas": [
        "^0.8.0"
      ],
      "artifacts": [
        "Context"
      ]
    },
    "/home/arpit/blockchain projects/CryptoDevsDAO/hardhat-code/contracts/FakeNFTMarketplace.sol": {
      "lastModificationDate": 1675753857817,
      "contentHash": "b07fa6fb47be72a260798e570b9414aa",
      "sourceName": "contracts/FakeNFTMarketplace.sol",
      "solcConfig": {
        "version": "0.8.17",
        "settings": {
          "optimizer": {
            "enabled": false,
            "runs": 200
          },
          "outputSelection": {
            "*": {
              "*": [
                "abi",
                "evm.bytecode",
                "evm.deployedBytecode",
                "evm.methodIdentifiers",
                "metadata"
              ],
              "": [
                "ast"
              ]
            }
          }
        }
      },
      "imports": [],
      "versionPragmas": [
        "^0.8.0"
      ],
      "artifacts": [
        "FakeNFTMarketplace"
      ]
    }
  }
}
